ZizhuZhangxianshengGongzhonggaoBeifenVol2/README.md
ZizhuZhangxianshengGongzhonggaoBeifenVol2/__init__.py
ZizhuZhangxianshengGongzhonggaoBeifenVol2/__main__.py
ZizhuZhangxianshengGongzhonggaoBeifenVol2/file.epub
ZizhuZhangxianshengGongzhonggaoBeifenVol2/index.html
ZizhuZhangxianshengGongzhonggaoBeifenVol2/css/__init__.py
ZizhuZhangxianshengGongzhonggaoBeifenVol2/css/annotations.css
ZizhuZhangxianshengGongzhonggaoBeifenVol2/css/main.css
ZizhuZhangxianshengGongzhonggaoBeifenVol2/css/normalize.css
ZizhuZhangxianshengGongzhonggaoBeifenVol2/css/popup.css
ZizhuZhangxianshengGongzhonggaoBeifenVol2/font/__init__.py
ZizhuZhangxianshengGongzhonggaoBeifenVol2/font/fontello.eot
ZizhuZhangxianshengGongzhonggaoBeifenVol2/font/fontello.svg
ZizhuZhangxianshengGongzhonggaoBeifenVol2/font/fontello.ttf
ZizhuZhangxianshengGongzhonggaoBeifenVol2/font/fontello.woff
ZizhuZhangxianshengGongzhonggaoBeifenVol2/img/__init__.py
ZizhuZhangxianshengGongzhonggaoBeifenVol2/img/annotator-glyph-sprite.png
ZizhuZhangxianshengGongzhonggaoBeifenVol2/img/annotator-icon-sprite.png
ZizhuZhangxianshengGongzhonggaoBeifenVol2/img/apple-touch-icon.png
ZizhuZhangxianshengGongzhonggaoBeifenVol2/img/cancelfullscreen.png
ZizhuZhangxianshengGongzhonggaoBeifenVol2/img/close.png
ZizhuZhangxianshengGongzhonggaoBeifenVol2/img/fullscreen.png
ZizhuZhangxianshengGongzhonggaoBeifenVol2/img/loader.gif
ZizhuZhangxianshengGongzhonggaoBeifenVol2/img/menu-icon.png
ZizhuZhangxianshengGongzhonggaoBeifenVol2/img/save.png
ZizhuZhangxianshengGongzhonggaoBeifenVol2/img/saved.png
ZizhuZhangxianshengGongzhonggaoBeifenVol2/img/settings-s.png
ZizhuZhangxianshengGongzhonggaoBeifenVol2/img/settings.png
ZizhuZhangxianshengGongzhonggaoBeifenVol2/img/star.png
ZizhuZhangxianshengGongzhonggaoBeifenVol2/js/__init__.py
ZizhuZhangxianshengGongzhonggaoBeifenVol2/js/epub.js
ZizhuZhangxianshengGongzhonggaoBeifenVol2/js/epub.min.js
ZizhuZhangxianshengGongzhonggaoBeifenVol2/js/epub.min.map
ZizhuZhangxianshengGongzhonggaoBeifenVol2/js/hooks.min.js
zizhu_zhangxiansheng_gongzhonggao_beifen_vol2-2022.10.10.0.dist-info/METADATA
zizhu_zhangxiansheng_gongzhonggao_beifen_vol2-2022.10.10.0.dist-info/WHEEL
zizhu_zhangxiansheng_gongzhonggao_beifen_vol2-2022.10.10.0.dist-info/entry_points.txt
zizhu_zhangxiansheng_gongzhonggao_beifen_vol2-2022.10.10.0.dist-info/top_level.txt
zizhu_zhangxiansheng_gongzhonggao_beifen_vol2-2022.10.10.0.dist-info/RECORD
